Metadata-Version: 1.1
Name: qt-multiprocessing
Version: 0.0.1
Summary: Library to have other PySide/PyQt widgets run in a separate process while allowing communication with the main process.
Home-page: https://github.com/justengel/qt_multiprocessing
Author: Justin Engel
Author-email: jtengel08@gmail.com
License: MIT
Download-URL: https://github.com/justengel/qt_multiprocessing/archive/v0.0.1.tar.gz
Keywords: qt multiprocessing,multiprocessing,event,loop,event loop,process
Platform: any
Classifier: Programming Language :: Python
Classifier: Programming Language :: Python :: 3
Classifier: Operating System :: OS Independent
